{"skeleton":{"hash":"vb19tmoeCCw","spine":"4.2.29","x":-143.5,"y":-143,"width":287,"height":286,"images":"../File AI/Asset Satellite esploso/","audio":"./audio"},"bones":[{"name":"root"},{"name":"Esplosione","parent":"root"}],"slots":[{"name":"Esplosione","bone":"Esplosione","attachment":"Esplosione"},{"name":"Satellite rotto 1","bone":"root"},{"name":"Pannello SX","bone":"root"}],"skins":[{"name":"default","attachments":{"Esplosione":{"Esplosione":{"width":287,"height":286}}}}],"animations":{"animation":{"slots":{"Esplosione":{"rgba":[{"time":0.1667,"color":"ffffffff"},{"time":0.3333,"color":"ffffff00"}]}},"bones":{"Esplosione":{"scale":[{"x":0.05,"y":0.05,"curve":[0.056,0.05,0.111,1.006,0.056,0.05,0.111,1.006]},{"time":0.1667,"x":1.006,"y":1.006,"curve":[0.222,1.006,0.278,0.05,0.222,1.006,0.278,0.05]},{"time":0.3333,"x":0.05,"y":0.05}]}}}}}